microSWIFTtelemetry/__init__.py
microSWIFTtelemetry/pull_telemetry.py
microSWIFTtelemetry/version.py
microSWIFTtelemetry/sbd/__init__.py
microSWIFTtelemetry/sbd/compile_sbd.py
microSWIFTtelemetry/sbd/definitions.py
microSWIFTtelemetry/sbd/read_sbd.py
microSWIFTtelemetry-0.3.7.dist-info/LICENSE
microSWIFTtelemetry-0.3.7.dist-info/METADATA
microSWIFTtelemetry-0.3.7.dist-info/WHEEL
microSWIFTtelemetry-0.3.7.dist-info/top_level.txt
microSWIFTtelemetry-0.3.7.dist-info/RECORD
