Metadata-Version: 2.1
Name: microSWIFTtelemetry
Version: 0.3.7
Summary: microSWIFTtelemetry: Python-based functionality for pulling telemetry from the microSWIFT wave buoy.
Home-page: https://github.com/SASlabgroup/microSWIFTtelemetry
Download-URL: 
Author: Jacob Davis
Author-email: davisjr@uw.edu
Maintainer: Jacob Davis
Maintainer-email: davisjr@uw.edu
License: MIT
Platform: OS Independent
Classifier: Intended Audience :: Science/Research
Classifier: License :: OSI Approved :: MIT License
Classifier: Operating System :: OS Independent
Classifier: Programming Language :: Python :: 3
Classifier: Topic :: Scientific/Engineering
Requires: matplotlib
Requires: numpy
Requires: pandas
Requires: xarray
Requires-Python: >= 3.7
License-File: LICENSE
Requires-Dist: matplotlib
Requires-Dist: numpy
Requires-Dist: pandas
Requires-Dist: xarray
